devpack/__init__.py
devpack/development.py
devpack/batch_tools/__init__.py
devpack/batch_tools/aliases.py
devpack/batch_tools/alls.py
devpack/batch_tools/authors.py
devpack/batch_tools/docs.py
devpack/batch_tools/entry_points.py
devpack/batch_tools/inits.py
devpack/batch_tools/privates.py
devpack/batch_tools/readmes.py
devpack/batch_tools/shebangs.py
devpack/batch_tools/typing_hints.py
devpack/entry_points/__init__.py
devpack/entry_points/batch.py
devpack/entry_points/cli.py
devpack/entry_points/versioning.py
devpack/versioning_tools/__init__.py
devpack/versioning_tools/bump.py
devpack-0.1.0.dist-info/LICENSE.md
devpack-0.1.0.dist-info/METADATA
devpack-0.1.0.dist-info/WHEEL
devpack-0.1.0.dist-info/entry_points.txt
devpack-0.1.0.dist-info/top_level.txt
devpack-0.1.0.dist-info/RECORD
